impact_stack/jwt/__init__.py
impact_stack/jwt/decorators.py
impact_stack/jwt/manager.py
impact_stack/jwt/organizations.py
impact_stack/jwt/permissions.py
impact_stack/jwt/pytest_plugin.py
impact_stack/jwt/session.py
impact_stack_jwt-0.1.0.dist-info/licenses/LICENSE
impact_stack_jwt-0.1.0.dist-info/METADATA
impact_stack_jwt-0.1.0.dist-info/WHEEL
impact_stack_jwt-0.1.0.dist-info/entry_points.txt
impact_stack_jwt-0.1.0.dist-info/top_level.txt
impact_stack_jwt-0.1.0.dist-info/RECORD
