Metadata-Version: 2.4
Name: impact-stack-jwt
Version: 0.1.0
Summary: JWT handling and permisson check related functionality for Impact Stack.
Author-email: Roman Zimmermann <roman@more-onion.com>
License-File: LICENSE
Requires-Dist: flask-jwt-extended
Provides-Extra: dev
Requires-Dist: black; extra == "dev"
Requires-Dist: django; extra == "dev"
Requires-Dist: flask; extra == "dev"
Requires-Dist: isort; extra == "dev"
Requires-Dist: pre-commit; extra == "dev"
Requires-Dist: pylint; extra == "dev"
Requires-Dist: pytest; extra == "dev"
Requires-Dist: pytest-cov; extra == "dev"
Requires-Dist: requests-mock; extra == "dev"
Requires-Dist: twine; extra == "dev"
Dynamic: license-file
